pymermaider-0.1.6.data/scripts/pymermaider.exe
pymermaider-0.1.6.dist-info/METADATA
pymermaider-0.1.6.dist-info/WHEEL
pymermaider-0.1.6.dist-info/licenses/LICENSE
pymermaider/__init__.py
pymermaider/__main__.py
pymermaider-0.1.6.dist-info/RECORD
